pweb_cli/__init__.py
pweb_cli/pweb_cli_bsw.py
pweb_cli/code-template/pwebsm.yml
pweb_cli/code-template/common/.gitignore
pweb_cli/code-template/common/README.md
pweb_cli/code-template/pweb/env.yml
pweb_cli/code-template/pweb/pweb_app.py
pweb_cli/code-template/pweb/setup.py
pweb_cli/code-template/pweb/application/__init__.py
pweb_cli/code-template/pweb/application/boot/.gitignore
pweb_cli/code-template/pweb/application/boot/README.md
pweb_cli/code-template/pweb/application/boot/setup.py
pweb_cli/code-template/pweb/application/boot/boot/__init__.py
pweb_cli/code-template/pweb/application/boot/boot/boot_module.py
pweb_cli/code-template/pweb/application/boot/boot/common/__init__.py
pweb_cli/code-template/pweb/application/boot/boot/controller/__init__.py
pweb_cli/code-template/pweb/application/boot/boot/controller/boot_static_controller.py
pweb_cli/code-template/pweb/application/boot/boot/controller/home_controller.py
pweb_cli/code-template/pweb/application/boot/boot/data/__init__.py
pweb_cli/code-template/pweb/application/boot/boot/dto/__init__.py
pweb_cli/code-template/pweb/application/boot/boot/model/__init__.py
pweb_cli/code-template/pweb/application/boot/boot/service/__init__.py
pweb_cli/code-template/pweb/application/boot/boot/template-assets/assets/css/style.css
pweb_cli/code-template/pweb/application/boot/boot/template-assets/assets/css/lib/bootstrap.min.css
pweb_cli/code-template/pweb/application/boot/boot/template-assets/assets/js/lib/bootstrap.bundle.min.js
pweb_cli/code-template/pweb/application/boot/boot/template-assets/templates/home/index.html
pweb_cli/code-template/pweb/application/config/__init__.py
pweb_cli/code-template/pweb/application/config/app_config.py
pweb_cli/code-template/pweb/application/config/asset_config.py
pweb_cli/code-template/pweb/application/config/module_registry.py
pweb_cli/code-template/pweb/module/.gitignore
pweb_cli/code-template/pweb/module/README.md
pweb_cli/code-template/pweb/module/__init__.py
pweb_cli-0.0.18.dist-info/LICENSE
pweb_cli-0.0.18.dist-info/METADATA
pweb_cli-0.0.18.dist-info/WHEEL
pweb_cli-0.0.18.dist-info/entry_points.txt
pweb_cli-0.0.18.dist-info/top_level.txt
pweb_cli-0.0.18.dist-info/RECORD
