Metadata-Version: 2.1
Name: pweb-cli
Version: 0.0.18
Summary: Command line interface for PWeb application, which allow to make PWeb work easy.
Home-page: https://github.com/banglafighter/pweb-cli
Author: Bangla Fighter
Author-email: banglafighter.com@gmail.com
License: Apache 2.0
Platform: any
Classifier: Intended Audience :: Developers
Classifier: License :: OSI Approved :: Apache Software License
Classifier: Programming Language :: Python
License-File: LICENSE
Requires-Dist: virtualenv
Requires-Dist: GitPython ==3.1.37
Requires-Dist: ppy-common
Requires-Dist: ppy-file-text
Requires-Dist: ppy-jsonyml
